{
  "resourceType" : "Bundle",
  "id" : "4dcbdfa8-9a2e-462e-bfbe-01808e393740",
  "meta" : {
    "lastUpdated" : "2024-04-09T11:42:02.127+00:00"
  },
  "type" : "collection",
  "entry" : [{
    "fullUrl" : "https://dhis2.org/fhir/ValueSet/animal-type",
    "resource" : {
      "resourceType" : "ValueSet",
      "text" : {
        "status" : "generated",
        "div" : "<div xmlns=\"http://www.w3.org/1999/xhtml\"><p style=\"border: black 1px dotted; background-color: #EEEEEE; padding: 8px; margin-bottom: 8px\">Expansion based on <a href=\"CodeSystem-animal-type.html\">codesystem Animal Type v0.1.0 (CodeSystem)</a></p><p>This value set contains 3 concepts.</p><table class=\"codes\"><tr><td style=\"white-space:nowrap\"><b>Code</b></td><td><b>System</b></td><td><b>Display</b></td></tr><tr><td style=\"white-space:nowrap\"><a name=\"https---dhis2.org-fhir-CodeSystem-animal-type-CAPTIVE\"> </a>\u00a0\u00a0<a href=\"CodeSystem-animal-type.html#animal-type-CAPTIVE\">CAPTIVE</a></td><td>https://dhis2.org/fhir/CodeSystem/animal-type</td><td>Captive</td></tr><tr><td style=\"white-space:nowrap\"><a name=\"https---dhis2.org-fhir-CodeSystem-animal-type-WILD\"> </a>\u00a0\u00a0<a href=\"CodeSystem-animal-type.html#animal-type-WILD\">WILD</a></td><td>https://dhis2.org/fhir/CodeSystem/animal-type</td><td>Wild</td></tr><tr><td style=\"white-space:nowrap\"><a name=\"https---dhis2.org-fhir-CodeSystem-animal-type-DOMESTIC\"> </a>\u00a0\u00a0<a href=\"CodeSystem-animal-type.html#animal-type-DOMESTIC\">DOMESTIC</a></td><td>https://dhis2.org/fhir/CodeSystem/animal-type</td><td>Domestic</td></tr></table></div>"
      },
      "url" : "https://dhis2.org/fhir/ValueSet/animal-type",
      "version" : "0.1.0",
      "name" : "AnimalTypeVS",
      "title" : "Animal Type",
      "status" : "draft",
      "date" : "2024-04-09T11:42:02+00:00",
      "expansion" : {
        "identifier" : "urn:uuid:c1a2ce79-ec10-4e01-95fb-3d874bf1e020",
        "timestamp" : "2024-04-09T11:42:10+00:00",
        "total" : 3,
        "offset" : 0,
        "parameter" : [{
          "name" : "count",
          "valueInteger" : 1000
        },
        {
          "name" : "offset",
          "valueInteger" : 0
        },
        {
          "name" : "excludeNested",
          "valueBoolean" : false
        },
        {
          "name" : "used-codesystem",
          "valueUri" : "https://dhis2.org/fhir/CodeSystem/animal-type|0.1.0"
        }],
        "contains" : [{
          "system" : "https://dhis2.org/fhir/CodeSystem/animal-type",
          "code" : "CAPTIVE",
          "display" : "Captive"
        },
        {
          "system" : "https://dhis2.org/fhir/CodeSystem/animal-type",
          "code" : "WILD",
          "display" : "Wild"
        },
        {
          "system" : "https://dhis2.org/fhir/CodeSystem/animal-type",
          "code" : "DOMESTIC",
          "display" : "Domestic"
        }]
      }
    }
  }]
}